omniindex/__init__.py
omniindex/api.py
omniindex-0.1.15.dist-info/LICENSE
omniindex-0.1.15.dist-info/METADATA
omniindex-0.1.15.dist-info/WHEEL
omniindex-0.1.15.dist-info/top_level.txt
omniindex-0.1.15.dist-info/RECORD
