Metadata-Version: 2.1
Name: omniindex
Version: 0.1.15
Summary: A Python package for interacting with the OmniIndex Homomorphic Encrypted Blockchain API
Home-page: https://github.com/OmniIndex/python
Author: James Stanbridge
Author-email: james@omniindex.io
Classifier: Development Status :: 4 - Beta
Classifier: Intended Audience :: Developers
Classifier: License :: OSI Approved :: MIT License
Classifier: Programming Language :: Python :: 3
Classifier: Programming Language :: Python :: 3.6
Classifier: Programming Language :: Python :: 3.7
Classifier: Programming Language :: Python :: 3.8
Classifier: Programming Language :: Python :: 3.9
Classifier: Programming Language :: Python :: 3.10
License-File: LICENSE
Requires-Dist: requests
Requires-Dist: pandas
Requires-Dist: pytest
Requires-Dist: simplejson
Requires-Dist: delorean
